mlflow_provider/__init__.py
mlflow_provider/__version__.py
mlflow_provider/hooks/__init__.py
mlflow_provider/hooks/base.py
mlflow_provider/hooks/client.py
mlflow_provider/hooks/deployment.py
mlflow_provider/hooks/pyfunc.py
mlflow_provider/operators/__init__.py
mlflow_provider/operators/deployment.py
mlflow_provider/operators/pyfunc.py
mlflow_provider/operators/registry.py
airflow_provider_mlflow-1.1.0.dist-info/LICENSE
airflow_provider_mlflow-1.1.0.dist-info/METADATA
airflow_provider_mlflow-1.1.0.dist-info/WHEEL
airflow_provider_mlflow-1.1.0.dist-info/top_level.txt
airflow_provider_mlflow-1.1.0.dist-info/RECORD
