Metadata-Version: 2.1
Name: airflow-provider-mlflow
Version: 1.1.0
Summary: Apache Airflow provider for MLflow
Home-page: https://github.com/astronomer/airflow-provider-mlflow
Author: Faisal Hoda
Author-email: faisal@astronomer.io
License: Apache License 2.0
Project-URL: Source Code, https://github.com/astronomer/airflow-provider-mlflow
Project-URL: Homepage, https://github.com/astronomer/airflow-provider-mlflow
Project-URL: Documentation, http://airflow-provider-mlflow.rtfd.io
Project-URL: Changelog, https://github.com/astronomer/airflow-provider-mlflow/blob/main/CHANGELOG.rst
Classifier: Environment :: Web Environment
Classifier: Framework :: Apache Airflow
Classifier: Framework :: Apache Airflow :: Provider
Classifier: Intended Audience :: Developers
Classifier: License :: OSI Approved :: Apache Software License
Classifier: Operating System :: OS Independent
Classifier: Programming Language :: Python
Classifier: Programming Language :: Python :: 3
Classifier: Programming Language :: Python :: 3.7
Classifier: Programming Language :: Python :: 3.8
Classifier: Programming Language :: Python :: 3.9
Requires-Python: >=3.8
Provides-Extra: dev
License-File: LICENSE
